{
  "title": "How-to Guides",
  "nav": [
    {
      "title": "Change payout address",
      "id": "change-payout-address"
    },
    {
      "title": "Migrate node",
      "id": "migrate-node"
    },
    {
      "title": "Troubleshoot offline node", 
      "id": "troubleshoot-offline-node"
    },
    {
      "title": "Fix database corruption",
      "id": "fix-database-corruption"
    },
    {
      "title": "Set up remote access",
      "id": "setup-remote-access"
    },
    {
      "title": "Monitor node performance",
      "id": "monitor-node-performance"
    }
  ]
}